algebraic_search/__init__.py
algebraic_search/boolean_query.py
algebraic_search/fuzzy_boolean_query.py
algebraic_search/result_query.py
algebraic_search-0.1.2.dist-info/LICENSE
algebraic_search-0.1.2.dist-info/METADATA
algebraic_search-0.1.2.dist-info/WHEEL
algebraic_search-0.1.2.dist-info/top_level.txt
algebraic_search-0.1.2.dist-info/RECORD
