Metadata-Version: 2.1
Name: algebraic-search
Version: 0.1.2
Summary: A Python library for algebraic search.
Home-page: https://github.com/queelius/algebraic_search
Author: Alex Towell
Author-email: lex@metafunctor.com
Classifier: Programming Language :: Python :: 3
Classifier: License :: OSI Approved :: MIT License
Classifier: Operating System :: OS Independent
Requires-Python: >=3.6
License-File: LICENSE
